fameflow/__init__.py
fameflow/app.py
fameflow-1.1.2.dist-info/LICENSE
fameflow-1.1.2.dist-info/METADATA
fameflow-1.1.2.dist-info/WHEEL
fameflow-1.1.2.dist-info/top_level.txt
fameflow-1.1.2.dist-info/RECORD
